hinterlist/__init__.py
hinterlist/check.py
hinterlist/detox.py
hinterlist-0.0.5.dist-info/LICENSE
hinterlist-0.0.5.dist-info/METADATA
hinterlist-0.0.5.dist-info/WHEEL
hinterlist-0.0.5.dist-info/top_level.txt
hinterlist-0.0.5.dist-info/RECORD
