Metadata-Version: 2.1
Name: hinterlist
Version: 0.0.5
Summary: INTERLIS Tools Collection
Home-page: https://github.com/eraymann/hinterlist
Author: Elias Raymann
Author-email: elias.raymann@swisstopo.ch
License: UNKNOWN
Platform: UNKNOWN
Classifier: Development Status :: 4 - Beta
Classifier: Programming Language :: Python :: 3.7
Classifier: License :: OSI Approved :: MIT License
Requires-Python: >=2.7
Requires-Dist: requests
